Workbook

Sheet Criteria
B3: USE FOR SELECTING ITEMS
B5: Classification Society | E5: Bureau Veritas
B6: Publication | E6: NR467 Steelships - July 2018 edition (entry into force 1 July 2018)
B8: Notations | E8: SHELTERED AREA
B15: SOLAS | E15: =IF(E8="SHELTERED AREA","No (Chapter I, Regulation 1 - Application (a) Unless expressly provided otherwise, the present regulations apply only to ships engaged on international voyages).","Yes.") -> No (Chapter I, Regulation 1 - Application (a) Unless expressly provided otherwise, the present regulations apply only to ships engaged on international voyages).
B17: Steam | E17: No
B19: Gross tonnage | E19: 48
B21: Propulsion engine power | E21: 0
B23: Heated fuel oil tanks | E23: No
B25: Battery room | E25: Yes

Sheet Titles
B2: 622 | C2: =IFERROR(VLOOKUP(B2,Systems!A:B,2,FALSE),"Various") -> Working / control air system | G2: =B2 -> 622
C4: Document information: | F4: Project information:
C5: Revision id | D5: 0 | F5: Client name | G5: Ministry of Transportation of Ontario, Canada
C6: Revision date | D6: 43157 | F6: Client number | G6: 2016-4006
C7: Revision author | D7: FvdM
F8: Classification | G8: Bureau Veritas
C9: Type of vessel | D9: Ro-Pax Ferry | F9: Class notation | G9: I ✠ Hull ✠ Mach, Ro-Ro Passenger Ship, Coastal Area, Ice Class 1B / COLD (-25), ✠ AVM-DPS / ✠ AUT-IMS / Battery System
C10: Project number | D10: DRFe6819 | F10: Flag state | G10: Canada
C11: Yard number | D11: 539317

Sheet Database
A1: Sys Id | B1: Sys name | C1: Subject | D1: Lloyd's Rules and Regulations for the Classification of Special Service Craft | E1: MCA - MSN 1792(M)2 - The Large Commercial Yacht Code (LY2) | F1: Vessel type / Code | G1: IMO IGC / IGC Code / Resolution MSC.391(95) (Liquefied Gases in Bulk) | H1: Bureau Veritas - NR467 - Steel ships | I1: RINA Rules | J1: Bureau Veritas - NR566 - Ships < 500GT | K1: MARPOL | L1: SOLAS | M1: Ministry of Transportation of Ontario - Technical Specification 2016-4006 | N1: Canadian supplement to the SOLAS convention - TP 15211E | O1: Government of Canada - Marine Machinery Regulations (SOR/90-264) | P1: Bureau Veritas - Inland Navigation Vessels | Q1: Danish Maritima Authority (DMA) | R1: Steam | S1: Rel | T1: Obv | U1: ExG | V1: StDE
S2: x | U2: =IF(OR(NOT(H2=""),NOT(M2="")),"","x")
A3: 371 | B3: =IFERROR(VLOOKUP(A3,Systems!A:B,2,FALSE),"Various") -> Ventilation system | C3: Pipes penetrating A or B class divisions | F3: Steelships | H3: 2.3.1 Uninsulated metallic pipes penetrating A or B class divisions shall be of materials having a melting temperature which exceeds 950°C for A-0 and 850°C for B-0 class divisions. | U3: =IF(OR(NOT(H3=""),NOT(M3="")),"","x")
A4: 371 | B4: =IFERROR(VLOOKUP(A4,Systems!A:B,2,FALSE),"Various") -> Ventilation system | C4: Pipes penetrating A or B class divisions | F4: Steelships | H4: 2.3.2 Where the Society may permit the conveying of oil and combustible liquids through accommodation and service spaces, the pipes conveying oil or combustible liquids shall be of a material approved by the Society having regard to the fire risk. | S4: x | T4: x | U4: =IF(OR(NOT(H4=""),NOT(M4="")),"","x")
A5: 371 | B5: =IFERROR(VLOOKUP(A5,Systems!A:B,2,FALSE),"Various") -> Ventilation system | C5: Battery room - warning notice for closing device | F5: Steelships | H5: 6-2-12.5.2 Where a battery compartment ventilator is required to be fitted with a closing device in accordance with Pt 3, Ch 12, 2.3 Closing appliances 2.3.9, a warning notice clearly stating the purpose of the closing device, for example: 'This closing device is to be kept open and only closed in the event of a fire or flooding – Explosive gas atmosphere' is to be provided at the closing device to mitigate the possibility of inadvertent closing of the ventilator. Furthermore, means to lock the battery compartment ventilators in the open position are to be provided. | U5: =IF(OR(NOT(H5=""),NOT(M5="")),"","x")
A6: 371 | B6: =IFERROR(VLOOKUP(A6,Systems!A:B,2,FALSE),"Various") -> Ventilation system | C6: Battery room - free air flow | F6: Battery room | H6: 6-2-12.5.3 Ducted natural ventilation may be employed for battery installations connected to a charging device with a power output of 2 kW or less, provided the exhaust duct can be run directly from the top of the compartment or box to the open air above, with no part of the duct more than 45° from the vertical. A suitable opening is also to be provided below the level of the top of the batteries, so as to ensure a free ventilation air flow. The ventilation duct is to have an area not less than 50 cm2 for every 1 m3 of battery compartment or box volume. | S6: x | U6: =IF(OR(NOT(H6=""),NOT(M6="")),"","x")
A7: 371 | B7: =IFERROR(VLOOKUP(A7,Systems!A:B,2,FALSE),"Various") -> Ventilation system | C7: Battery room - natural or mechanical | F7: Battery room | H7: 6-2-12.5.4 Where natural ventilation is impracticable or insufficient, mechanical ventilation is to be provided, with the air inlet located near the floor and the exhaust at the top of the compartment. | S7: x | U7: =IF(OR(NOT(H7=""),NOT(M7="")),"","x")
A8: 371 | B8: =IFERROR(VLOOKUP(A8,Systems!A:B,2,FALSE),"Various") -> Ventilation system | C8: Battery room - mechanical ventilation for charged batteries | F8: Battery room | H8: 6-2-12.5.5 Mechanical exhaust ventilation complying with Pt 6, Ch 2, 12.5 Ventilation 12.5.9 is to be provided for battery installations connected to a charging device with a total maximum power output of more than 2 kW. Also, to minimise the possibility of oxygen enrichment, compartments and spaces containing batteries with boost charging facilities are to be provided with mechanical exhaust ventilation irrespective of the charging device power output. | S8: x | U8: =IF(OR(NOT(H8=""),NOT(M8="")),"","x")
A9: 371 | B9: =IFERROR(VLOOKUP(A9,Systems!A:B,2,FALSE),"Various") -> Ventilation system | C9: Battery room - separate vent | F9: Battery room | H9: 6-2-12.5.6 The ventilation system for battery compartments and boxes, other than boxes located on open deck or in spaces to which Pt 6, Ch 2, 12.3 Location 12.3.2, Pt 6, Ch 2, 12.3 Location 12.3.3 and Pt 6, Ch 2, 12.3 Location 12.3.5 refer, is to be separate from other ventilation systems. The exhaust ducting is to be led to a location in the open air, where any gases can be safely diluted, away from possible sources of ignition and openings into spaces where gases may accumulate. | S9: x | U9: =IF(OR(NOT(H9=""),NOT(M9="")),"","x")
A10: 371 | B10: =IFERROR(VLOOKUP(A10,Systems!A:B,2,FALSE),"Various") -> Ventilation system | C10: Battery room - fan motor | F10: Battery room | H10: 6-2-12.5.7 Fan motors associated with exhaust ducts from battery compartments are to be placed external to the ducts and the compartments. | S10: x | U10: =IF(OR(NOT(H10=""),NOT(M10="")),"","x")
A11: 371 | B11: =IFERROR(VLOOKUP(A11,Systems!A:B,2,FALSE),"Various") -> Ventilation system | C11: Battery room - fan material | F11: Battery room | H11: 6-2-12.5.8 Ventilating fans for battery compartments are to be so constructed and be of material such as to minimise risk of sparking in the event of the impeller touching the casing. Non-metallic-impellers are to be of an anti-static material. | S11: x | U11: =IF(OR(NOT(H11=""),NOT(M11="")),"","x")
A12: 371 | B12: =IFERROR(VLOOKUP(A12,Systems!A:B,2,FALSE),"Various") -> Ventilation system | C12: Battery room - vent openings | F12: Battery room | H12: 6-2-12.5.9 Battery boxes are to be provided with sufficient ventilation openings located so as to avoid accumulation of flammable gas whilst preventing the entrance of rain or spray. | S12: x | U12: =IF(OR(NOT(H12=""),NOT(M12="")),"","x")
A13: 000 | B13: =IFERROR(VLOOKUP(A13,Systems!A:B,2,FALSE),"Various") -> Project data | C13: General definition | F13: Battery room | H13: A-1-1-1.2.1 Essential service is intended to mean a service necessary for a ship to proceed at sea, be steered or manoeuvred, or undertake activities connected with its operation, and for the safety of life, as far as class is concerned. | S13: x | U13: =IF(OR(NOT(H13=""),NOT(M13="")),"","x")
A14: 100 | B14: =IFERROR(VLOOKUP(A14,Systems!A:B,2,FALSE),"Various") -> Tank arrangement | C14: Adjacent or not | F14: Battery room | H14: B-2-1-2.1.4 Where a corner to corner situation occurs, tanks are not be considered to be adjacent. Adjacent tanks not separated by cofferdams are to have adequate dimensions to ensure easy inspection. | P14: B-2-1-2.1.4 Where a corner to corner situation occurs, tanks are not be considered to be adjacent. Adjacent tanks not separated by cofferdams are to have adequate dimensions to ensure easy inspection. | S14: x | U14: =IF(OR(NOT(H14=""),NOT(M14="")),"","x")
A15: 100 | B15: =IFERROR(VLOOKUP(A15,Systems!A:B,2,FALSE),"Various") -> Tank arrangement | C15: Cofferdams between tanks | F15: Battery room | H15: B-2-2-2.1.1 Cofferdams are to be provided between: - fuel oil tanks and lubricating oil tanks - compartments intended for liquid hydrocarbons (fuel oil, lubricating oil) and compartments intended for fresh water (drinking water, water for propelling machinery and boilers) - compartments intended for liquid hydrocarbons (fuel oil, lubricating oil) and tanks intended for the carriage of liquid foam for fire extinguishing. | P15: B-2-1-2.1.1 Cofferdams are to be provided between compartments intended for liquid hydrocarbons (fuel oil, lubricating oil) and those intended for fresh water (drinking water, water for propelling machinery and boilers) as well as tanks intended for the carriage of liquid foam for fire extinguishing. | S15: x | U15: =IF(OR(NOT(H15=""),NOT(M15="")),"","x")
A16: 100 | B16: =IFERROR(VLOOKUP(A16,Systems!A:B,2,FALSE),"Various") -> Tank arrangement | C16: Exemptions for cofferdams | F16: Battery room | H16: B-2-2-2.1.2 Cofferdams separating: - fuel oil tanks from lubricating oil tanks - lubricating oil tanks from compartments intended for fresh water or boiler feed water - lubricating oil tanks from those intended for the carriage of liquid foam for fire extinguishing may not be required when deemed impracticable or unreasonable by the Society in relation to the characteristics and dimensions of the spaces containing such tanks, provided that: - the thickness of common boundary plates of adjacent tanks is increased, with respect to the thickness obtained according to Ch 7, Sec 1, by 2 mm in the case of tanks carrying fresh water or boiler feed water, and by 1 mm in all other cases - the sum of the throats of the weld fillets at the edges of these plates is not less than the thickness of the plates themselves - the structural test is carried out with a head increased by 1 m with respect to Ch 11, Sec 3, [1.4]. 2.1.3 Vented cofferdam may be required to separate heated oil fuel tanks from enclosed spaces located directly above (see Pt C, Ch 1, Sec 10, [11.7.2], item a)). | P16: B-2-1-2.1.2 Cofferdams separating fuel oil tanks from lubricating oil tanks and the latter from those intended for the carriage of liquid foam for fire extinguishing or fresh water or boiler feed water may not be required when deemed impracticable or unreasonable by the Society in relation to the characteristics and dimensions of the spaces containing such tanks, provided that: - the thickness of common boundary plates of adjacent tanks is increased, with respect to the thickness obtained according to Ch 5, Sec 5, [4] by 2 mm in the case of tanks carrying fresh water or boiler feed water, and by 1 mm in all other cases - the sum of the throats of the weld fillets at the edges of these plates is not less than the thickness of the plates themselves - the structural test is carried out with a head increased by 1 m with respect to Ch 3, Sec 4, [5.1]. | S16: x | U16: =IF(OR(NOT(H16=""),NOT(M16="")),"","x")
A17: 311 | B17: =IFERROR(VLOOKUP(A17,Systems!A:B,2,FALSE),"Various") -> Bilge system | C17: Bilge wells in double bottoms | F17: Battery room | H17: B-2-2-3.1.3 Small wells constructed in the double bottom in connection with drainage arrangement are not to extend downward more than necessary. The vertical distance from the bottom of such a well to a plane coinciding with the keel line is not to be less than h/2 or 500 mm, whichever is greater, or compliance with requirement defined in Ch 3, Sec 3, [3.4.3] is to be shown for that part of the ship. Other wells (e.g. for lubricating oil under main engines) may be permitted by the Society if satisfied that the arrangements give protection equivalent to that afforded by a double bottom complying with this regulation. Proof of equivalent protection is to be shown by demonstrating that the ship is capable of withstanding bottom damages as specified in Ch 3, Sec 3, [3.4.3]. Alternatively, wells for lubricating oil below main engines may protrude into the double bottom below the boundary line defined by the distance h provided that the vertical distance between the well bottom and a plane coinciding with the keel line is not less than h/2 or 500 mm, whichever is the greater. For a cargo ship of less than 80 m in length, the arrangements are to provide a level of safety to the satisfaction of the Society. | P17: B-2-1-2.1.4 Where a corner to corner situation occurs, tanks are not be considered to be adjacent. Adjacent tanks not separated by cofferdams are to have adequate dimensions to ensure easy inspection. | S17: x | U17: =IF(OR(NOT(H17=""),NOT(M17="")),"","x")
A18: 100 | B18: =IFERROR(VLOOKUP(A18,Systems!A:B,2,FALSE),"Various") -> Tank arrangement | C18: Peak tanks | F18: Battery room | H18: B-2-2-4.1 The fore peak and other compartments located forward of the collision bulkhead cannot be used for the carriage of fuel oil or other flammable products. | P18: B-2-1-2.2.1 The fore peak and other compartments located forward of the collision bulkhead cannot be used for the carriage of fuel oil or other flammable products. | S18: x | U18: =IF(OR(NOT(H18=""),NOT(M18="")),"","x")
A19: 100 | B19: =IFERROR(VLOOKUP(A19,Systems!A:B,2,FALSE),"Various") -> Tank arrangement | C19: Fuel oil tanks | D19: 15-3-3.17.1 In a yacht in which fuel oil is used, the arrangements for the storage, distribution and utilisation of the fuel oil are to be such as to ensure the safety of the yacht and persons on board. For details, see Pt 15, Ch 3 Machinery Piping Systems. | F19: Battery room | H19: B-2-2-8.1.1 The arrangements for the storage, distribution and utilisation of the fuel oil are to be such as to ensure the safety of the ship and persons on board. | S19: x | U19: =IF(OR(NOT(H19=""),NOT(M19="")),"","x")
A20: 100 | B20: =IFERROR(VLOOKUP(A20,Systems!A:B,2,FALSE),"Various") -> Tank arrangement | C20: Fuel oil tanks | D20: 15-3-3.17.2 As far as practicable, fuel oil tanks are to be part of the yacht's structure and are to be located outside Category ‘A' machinery spaces. 15-3-3.17.3 Where fuel oil tanks, other than double bottom tanks, are necessarily located adjacent to or within Category ‘A' machinery spaces, at least one of their vertical sides is to be contiguous to the machinery space boundaries, and is preferably to have a common boundary with the double bottom tanks, and the area of the tank boundary common with the machinery spaces is to be kept to a minimum. Where the vertical boundary of a tank directly exposed to a machinery space meets the yacht's side plating at an acute angle, a small horizontal surface at the base of the tank, necessary to accommodate practical constructional considerations may be permitted. If the arrangement of the machinery is such that a tank with a large horizontal surface at the base is necessary then a cofferdam with suitable ventilation arrangements, to protect the base of the tank from the effect of a machinery space fire, will be specially considered. See also Pt 15, Ch 3 Machinery Piping Systems. Fuel oil tanks situated within the boundaries of Category ‘A' machinery spaces are not to contain fuel oil having a flashpoint of less than 60°C. The use of free-standing fuel oil tanks is prohibited. | F20: Battery room | H20: B-2-2-8.1.2 As far as practicable, fuel oil tanks are to be part of the ship's structure and are to be located outside machinery spaces of category A. Where fuel oil tanks, other than double bottom tanks, are necessarily located adjacent to or within machinery spaces of category A, at least one of their vertical sides is to be contiguous to the machinery space boundaries, they are preferably to have a common boundary with the double bottom tanks and the area of the tank boundary common with the machinery spaces is to be kept to a minimum. Where such tanks are situated within the boundaries of machinery spaces of category A, they may not contain fuel oil having a flashpoint of less than 60°C. | S20: x | U20: =IF(OR(NOT(H20=""),NOT(M20="")),"","x")
A21: 100 | B21: =IFERROR(VLOOKUP(A21,Systems!A:B,2,FALSE),"Various") -> Tank arrangement | C21: Fuel oil tanks | F21: Battery room | H21: B-2-2-8.1.3 Fuel oil tanks may not be located where spillage or leakage therefrom can constitute a hazard by falling on heated surfaces. Precautions are to be taken to prevent any oil that may escape under pressure from any pump, filter or heater from coming into contact with heated surfaces. Fuel oil tanks in boiler spaces may not be located immediately above the boilers or in areas subjected to high temperatures, unless special arrangements are provided in agreement with the Society. | S21: x | U21: =IF(OR(NOT(H21=""),NOT(M21="")),"","x")
A22: 132 | B22: =IFERROR(VLOOKUP(A22,Systems!A:B,2,FALSE),"Various") -> Manholes / manhole covers | C22: Double bottom | F22: Battery room | H22: B-2-3-2.1 Inner bottom manholes Inner bottom manholes are to be not less than 0,40 m x 0,40 m. Their number and location are to be so arranged as to provide convenient access to any part of the double bottom. Inner bottom manholes are to be closed by watertight plate covers. Doubling plates are to be fitted on the covers, where secured by bolts. Where no ceiling is fitted, covers are to be adequately protected from damage by the cargo. | P22: B-2-1-3.1.1 Inner bottom manholes Inner bottom manholes are to be not less than 0,40 m x 0,40 m. Their number and location are to be so arranged as to provide convenient access to any part of the double bottom. Inner bottom manholes are to be closed by watertight plate covers. Doubling plates are to be fitted on the covers, where secured by bolts. Where no ceiling is fitted, covers are to be adequately protected from damage by the cargo. | S22: x | U22: =IF(OR(NOT(H22=""),NOT(M22="")),"","x")
A23: 143 | B23: =IFERROR(VLOOKUP(A23,Systems!A:B,2,FALSE),"Various") -> Platforms / gratings | C23: Double bottom | F23: Battery room | H23: B-2-3-2.2 Floor and girder manholes Manholes are to be provided in floors and girders so as to provide convenient access to all parts of the double bottom. The size of manholes and lightening holes in floors and girders is, in general, to be less than 50 per cent of the local height of the double bottom. Where manholes of greater sizes are needed, edge reinforcement by means of flat bar rings or other suitable stiffeners may be required. Manholes may not be cut into the continuous centreline girder or floors and girders below pillars, except where allowed by the Society on a case by case basis. | P23: B-2-1-3.1.2 Floor and girder manholes Manholes are to be provided in floors and girders so as to provide convenient access to all parts of the double bottom. The size of manholes and lightening holes in floors and girders is, in general, to be less than 50 per cent of the local height of the double bottom. Where manholes of greater sizes are needed, edge reinforcement by means of flat bar rings or other suitable stiffeners may be required. Manholes may not be cut into the continuous centreline girder or floors and girders below pillars, except where allowed by the Society on a case by case basis. | S23: x | U23: =IF(OR(NOT(H23=""),NOT(M23="")),"","x")
A24: 132 | B24: =IFERROR(VLOOKUP(A24,Systems!A:B,2,FALSE),"Various") -> Manholes / manhole covers | C24: Access to tanks | F24: Battery room | H24: B-2-3-3.2.1 Tanks and subdivisions of tanks having lengths of 35 m and above are to be fitted with at least two access hatchways and ladders, as far apart as practicable longitudinally. Tanks less than 35 m in length are to be served by at least one access hatchway and ladder. | P24: B-2-1-3.2.1 Tanks and subdivisions of tanks having lengths of 35 m and above are to be fitted with at least two access hatchways and ladders, as far apart as practicable longitudinally. Tanks less than 35 m in length are to be served by at least one access hatchway and ladder. | S24: x | U24: =IF(OR(NOT(H24=""),NOT(M24="")),"","x")
A25: 132 | B25: =IFERROR(VLOOKUP(A25,Systems!A:B,2,FALSE),"Various") -> Manholes / manhole covers | C25: Access to tanks | F25: Battery room | H25: B-2-3-3.2.2 The dimensions of any access hatchway are to be sufficient to allow a person wearing a self-contained breathing apparatus to ascend or descend the ladder without obstruction and also to provide a clear opening to facilitate the hoisting of an injured person from the bottom of the tank. In no case is the clear opening to be less than 0,36 m2 and its length 0,50 m. | P25: B-2-1-3.2.2 The dimensions of any access hatchway are to be sufficient to allow a person wearing a self-contained breathing apparatus to ascend or descend the ladder without obstruction and also to provide a clear opening to facilitate the hoisting of an injured person from the bottom of the tank. In no case is the clear opening to be less than 0,36 m2 and its length 0,50 m. | S25: x | U25: =IF(OR(NOT(H25=""),NOT(M25="")),"","x")
A26: 132 | B26: =IFERROR(VLOOKUP(A26,Systems!A:B,2,FALSE),"Various") -> Manholes / manhole covers | C26: Access within tanks | F26: Battery room | H26: B-2-3-3.3.4 Manholes Where manholes are fitted, access is to be facilitated by means of steps and hand grips with platform landings on each side. | P26: B-2-1-3.3.2 Manholes Where manholes are fitted, access is to be facilitated by means of steps and hand grips with platform landings on each side. | S26: x | U26: =IF(OR(NOT(H26=""),NOT(M26="")),"","x")
A27: 311 312 313 346 | B27: =IFERROR(VLOOKUP(A27,Systems!A:B,2,FALSE),"Various") -> Various | C27: Progressive flooding - Definition | F27: Battery room | H27: B-3-3-3.3.1 Progressive flooding is the additional flooding of spaces which were not previously assumed to be damaged. Such additional flooding may occur through openings or pipes as indicated in [3.3.2] and [3.3.3]. | S27: x | T27: x | U27: =IF(OR(NOT(H27=""),NOT(M27="")),"","x")
A28: 311 312 313 346 | B28: =IFERROR(VLOOKUP(A28,Systems!A:B,2,FALSE),"Various") -> Various | C28: Progressive flooding - Openings categories | F28: Battery room | H28: B-3-3-3.3.2 Openings The openings may be listed in the following categories, depending on their means of closure: - Unprotected openings may lead to progressive flooding if they are situated within the range of the positive righting lever curve or if they are located below the waterline after damage (at any stage of flooding ). Unprotected openings are openings which are not fitted with at least weathertight means of closure, or ventilators that have to remain open to supply air to the engine room or emergency generator room for the effective operation of the ship. - Openings fitted with weathertight means of closure are not able to sustain a constant head of water, but they can be intermittently immersed within the positive range of stability. Weathertight openings may lead to progressive flooding if they are located below the waterline after damage (at any stage of flooding ). - Internal openings fitted with semi-watertight means of closure are able to sustain a constant head of water corresponding to the immersion relevant to the highest waterline after damage at the equilibrium of the intermediate stages of flooding. Semi-watertight openings may lead to progressive flooding if they are located below the final equilibrium waterline after damage. - Internal openings fitted with watertight means of closure are able to sustain a constant head of water corresponding to the distance between the lowest edge of this opening and the bulkhead/freeboard deck. Air pipe closing devices complying with Pt C, Ch 1, Sec 10, [9.1.6] may not be considered watertight, unless additional arrangements are fitted in order to demonstrate that such closing devices are effectively watertight. The pressure/vacuum valves (PV valves) currently installed on tankers do not theoretically provide complete watertightness. Manhole covers may be considered watertight provided the cover is fitted with bolts located such that the distance between their axes is less than five times the bolt's diameter. Access hatch covers leading to tanks may be considered watertight. Watertight openings do not lead to progressive flooding . | S28: x | U28: =IF(OR(NOT(H28=""),NOT(M28="")),"","x")
A29: 311 312 313 346 | B29: =IFERROR(VLOOKUP(A29,Systems!A:B,2,FALSE),"Various") -> Various | C29: Progressive flooding - Through pipes | F29: Battery room | H29: B-3-3-3.3.3 Progressive flooding through pipes may occur when: - the pipes and connected valves are located within the assumed damage, and no valves are fitted outside the damage - the pipes, even if located outside the damage, satisfy all of the following conditions: -- the pipe connects a damaged space to one or more spaces located outside the damage -- the highest vertical position of the pipe is below the waterline, and -- no valves are fitted. The possibility of progressive flooding through ballast piping passing through the assumed extent of damage, where positive action valves are not fitted to the ballast system at the open ends of the pipes in the tanks served, is to be considered. Where remote control systems are fitted to ballast valves and these controls pass through the assumed extent of damage, then the effect of damage to the system is to be considered to ensure that the valves would remain closed in that event. If pipes, ducts or tunnels are situated within assumed flooded compartments, arrangements are to be made to ensure that progressive flooding cannot thereby extend to compartments other than those assumed flooded. However, the Society may permit minor progressive flooding if it is demonstrated that the additional flooding of those compartments cannot lead to the capsizing or the sinking of the ship. Requirements relative to the prevention of progressive flooding are specified in Pt C, Ch 1, Sec 10, [5.5]. | J29: 1-3-3.3.1 If pipes, ducts trunks or tunnels are situated within the assumed extent of damage, arrangements are to be made to ensure that progressive flooding cannot thereby extend to compartments other than those assumed to be floodable for each case of damage. | L29: MSC/Circular.406/Rev.1 - Guidelines 3 | S29: x | U29: =IF(OR(NOT(H29=""),NOT(M29="")),"","x")
A30: 102 31x 331 341 | B30: =IFERROR(VLOOKUP(A30,Systems!A:B,2,FALSE),"Various") -> Various | C30: Hull piping - Material | F30: Battery room | H30: B-6-7-5.1.1 The scuppers and discharge pipes are to be constructed of steel. Other equivalent materials are considered by the Society on a case by case basis. | P30: B-6-7-5.1.1 The scuppers and discharge pipes are to be constructed of steel. Other equivalent materials are considered by the Society on a case by case basis. | S30: x | U30: =IF(OR(NOT(H30=""),NOT(M30="")),"","x")
A31: 311 | B31: =IFERROR(VLOOKUP(A31,Systems!A:B,2,FALSE),"Various") -> Bilge system | C31: Arrangement | F31: IGC Code | G31: 3.7.1.1. Where cargo is carried in a cargo containment system not requiring a secondary barrier, hold spaces should be provided with suitable drainage arrangements not connected with the machinery space. Means of detecting any leakage should be provided.
A32: 311 | B32: =IFERROR(VLOOKUP(A32,Systems!A:B,2,FALSE),"Various") -> Bilge system | C32: Arrangement | F32: IGC Code | G32: 3.7.1.2. Where there is a secondary barrier, suitable drainage arrangements for dealing with any leakage into the hold or insulation spaces through adjacent ship structure should be provided. The suction should not be led to pumps inside the machinery space. Means of detecting such leakage should be provided.
A33: 311 | B33: =IFERROR(VLOOKUP(A33,Systems!A:B,2,FALSE),"Various") -> Bilge system | C33: Arrangement | F33: IGC Code | G33: 3.7.2.1. The hold or interbarrier spaces of Type A independent tank ships should be provided with a drainage system suitable for handling liquid cargo in the event of cargo tank leakage or rupture. Such arrangements should provide for the return of any cargo leakage to the liquid cargo piping.
A34: 311 | B34: =IFERROR(VLOOKUP(A34,Systems!A:B,2,FALSE),"Various") -> Bilge system | C34: Arrangement | F34: IGC Code | G34: 3.7.2.2. Arrangements referred to in 3.7.2.1 should be provided with a removable spool piece.
A35: 311 | B35: =IFERROR(VLOOKUP(A35,Systems!A:B,2,FALSE),"Various") -> Bilge system | C35: Arrangement | F35: IGC Code | G35: 3.7.3. In case of internal insulation tanks, means of detecting leakage and drainage arrangements are not required for interbarrier spaces and spaces between the secondary barrier and the inner hull or independent tank structure which are completely filled by insulation material complying with 4.9.7.2
A36: 312 | B36: =IFERROR(VLOOKUP(A36,Systems!A:B,2,FALSE),"Various") -> Ballast system | C36: Arrangement | F36: IGC Code | G36: 3.7.4. Ballast spaces, including wet duct keels used as ballast piping, fuel-oil tanks and gas-safe spaces may be connected to pumps in the machinery spaces. Dry duct keels with ballast piping passing through, may be connected to pumps in the machinery spaces, provided the connections are led directly to the pumps and the discharge from the pumps lead directly overboard with no valves or manifolds in either line which could connect the line from the duct keel to lines serving gas-safe spaces. Pump vents should not be open to machinery spaces.
A37: 321 | B37: =IFERROR(VLOOKUP(A37,Systems!A:B,2,FALSE),"Various") -> Fuel transfer system | C37: ESD valve requirements | F37: IGC Code | G37: 18.10.2.1.2 ESD valves shall be remotely operated, be of the fail-closed type (closed on loss of actuating power), be capable of local manual closure and have positive indication of the actual valve position. As an alternative to the local manual closing of the ESD valve, a manually operated shut-off valve in series with the ESD valve shall be permitted. The manual valve shall be located adjacent to the ESD valve. Provisions shall be made to handle trapped liquid should the ESD valve close while the manual valve is also closed.
A38: 321 | B38: =IFERROR(VLOOKUP(A38,Systems!A:B,2,FALSE),"Various") -> Fuel transfer system | C38: ESD valve requirements | F38: IGC Code | G38: 18.10.2.1.3 ESD valves in liquid piping systems shall close fully and smoothly within 30 s of actuation. Information about the closure time of the valves and their operatingcharacteristics shall be available on board, and the closing time shall be verifiable and repeatable.
A39: 321 | B39: =IFERROR(VLOOKUP(A39,Systems!A:B,2,FALSE),"Various") -> Fuel transfer system | C39: Ship-shore and ship-ship manifold connections | G39: 18.10.2.2 One ESD valve shall be provided at each manifold connection. Cargo manifold connections not being used for transfer operations shall be blanked with blank flanges rated for the design pressure of the pipeline system.
A40: 321 | B40: =IFERROR(VLOOKUP(A40,Systems!A:B,2,FALSE),"Various") -> Fuel transfer system | C40: Number of ESD valves | G40: 5.5.1.2 In addition, remotely operated valves shall also be fitted, as appropriate, as part of the emergency shutdown (ESD) system the purpose of which is to stop cargo flowor leakage in the event of an emergency when cargo liquid or vapour transfer is in progress. The ESD system is intended to return the cargo system to a safe static condition so that any remedial action can be taken. Due regard shall be given in the design of the ESD system to avoid the generation of surge pressures within the cargo transfer pipework. The equipment to be shut down on ESD activation includes manifold valves during loading or discharge, any pump or compressor, etc., transferring cargo internally or externally (e.g. to shore or another ship/barge) and cargo tank valves, if the MARVS exceeds 0.07 MPa.
A41: 321 | B41: =IFERROR(VLOOKUP(A41,Systems!A:B,2,FALSE),"Various") -> Fuel transfer system | C41: Cargo manifold connections | G41: 5.5.3.1 One remotely controlled ESD valve shall be provided at each cargo transfer connection in use to stop liquid and vapour transfer to or from the ship. Transfer connections not in use shall be isolated with suitable blank flanges.
A42: 321 | B42: =IFERROR(VLOOKUP(A42,Systems!A:B,2,FALSE),"Various") -> Fuel transfer system | C42: Cargo manifold connections | G42: 5.5.3.2 If the cargo tank MARVS exceeds 0.07 MPa, an additional manual valve shall be provided for each transfer connection in use, and may be inboard or outboard of the ESD valve to suit the ship's design.
A43: 321 | B43: =IFERROR(VLOOKUP(A43,Systems!A:B,2,FALSE),"Various") -> Fuel transfer system | C43: Cargo manifold connections | G43: 5.5.4 Excess flow valves may be used in lieu of ESD valves, if the diameter of the protected pipe does not exceed 50 mm. Excess flow valves shall close automatically at the rated closing flow of vapour or liquid as specified by the manufacturer. The piping including fittings, valves and appurtenances protected by an excess flow valve shall have a capacity greater than the rated closing flow of the excess flow valve. Excess flow valves may be designed with a bypass not exceeding the area of a 1 mm diameter circular opening to allow equalization of pressure after a shutdown activation.
A44: 321 | B44: =IFERROR(VLOOKUP(A44,Systems!A:B,2,FALSE),"Various") -> Fuel transfer system | C44: Cargo manifold connections | G44: 5.5.5 Cargo tank connections for gauging or measuring devices need not be equipped with excess flow valves or ESD valves, provided that the devices are constructed so that the outward flow of tank contents cannot exceed that passed by a 1.5 mm diameter circular hole.
A45: 321 | B45: =IFERROR(VLOOKUP(A45,Systems!A:B,2,FALSE),"Various") -> Fuel transfer system | C45: Cargo manifold connections | G45: 5.5.6 All pipelines or components which may be isolated in a liquid full condition shall be protected with relief valves for thermal expansion and evaporation.
A46: 635 690 | B46: =IFERROR(VLOOKUP(A46,Systems!A:B,2,FALSE),"Various") -> Various | C46: Design vapor pressure | F46: IGC Code | G46: 4.2.6.1. The design vapour pressure Po is the maximum gauge pressure at the top of the tank which has been used in the design of the tank.
A47: 635 690 | B47: =IFERROR(VLOOKUP(A47,Systems!A:B,2,FALSE),"Various") -> Various | C47: Design vapor pressure | F47: IGC Code | G47: 4.2.6.2. For cargo tanks where there is no temperature control and where the pressure of the cargo is dictated only by the ambient temperature, Po should not be less than the gauge vapour pressure of the cargo at a temperature of 45°C. However, lesser values of this temperature may be accepted by the Administration for ships operating in restricted areas or on voyages of restricted duration and account may be taken in such cases of any insulation of the tanks. Conversely, higher values of this temperature may be required for ships permanently operating in areas of high ambient temperature.
A48: 635 690 | B48: =IFERROR(VLOOKUP(A48,Systems!A:B,2,FALSE),"Various") -> Various | C48: Design vapor pressure | F48: IGC Code | G48: 4.2.6.3. In all cases, including 4.2.6.2, Po should not be less than MARVS.
A49: 635 690 | B49: =IFERROR(VLOOKUP(A49,Systems!A:B,2,FALSE),"Various") -> Various | C49: Design vapor pressure | F49: IGC Code | G49: 4.2.6.4. Subject to special consideration by the Administration and to the limitations given in 4.2.1, 4.2.2, 4.2.3, 4.2.4 and 4.2.5 for the various tank types, a vapour pressure higher than Po may be accepted in harbour conditions, where dynamic loads are reduced.
A50: 635 690 | B50: =IFERROR(VLOOKUP(A50,Systems!A:B,2,FALSE),"Various") -> Various | C50: Design temperature | F50: IGC Code | G50: 4.2.7 The design temperature for selection of materials is the minimum temperature at which cargo may be loaded or transported in the cargo tanks. Provision to the satisfaction of the Administration should be made to ensure that the tank or cargo temperature cannot be lowered below the design temperature.
A51: 635 690 | B51: =IFERROR(VLOOKUP(A51,Systems!A:B,2,FALSE),"Various") -> Various | C51: Cargo and process piping - General | F51: IGC Code | G51: 5.2.1.1. The requirements of sections 5.2, 5.3, 5.4 and 5.5 apply to product and process piping including vapour piping and vent lines of safety valves or similar piping. Instrument piping not containing cargo is exempt from these requirements.
A52: 635 690 | B52: =IFERROR(VLOOKUP(A52,Systems!A:B,2,FALSE),"Various") -> Various | C52: Cargo and process piping - General | F52: IGC Code | G52: 5.2.1.2. Provision should be made by the use of offsets, loops, bends, mechanical expansion joints such as bellows, slip joints and ball joints or similar suitable means to protect the piping, piping system components and cargo tanks from excessive stresses due to thermal movement and from movements of the tank and hull structure. Where mechanical expansion joints are used in piping they should be held to a minimum and, where located outside cargo tanks, should be of the bellows type.
A53: 635 690 | B53: =IFERROR(VLOOKUP(A53,Systems!A:B,2,FALSE),"Various") -> Various | C53: Cargo and process piping - General | F53: IGC Code | G53: 5.2.1.3. Low-temperature piping should be thermally isolated from the adjacent hull structure, where necessary, to prevent the temperature of the hull from falling below the design temperature of the hull material. Where liquid piping is dismantled regularly, or where liquid leakage may be anticipated, such as at shore connections and at pump seals, protection for the hull beneath should be provided.
A54: 635 690 | B54: =IFERROR(VLOOKUP(A54,Systems!A:B,2,FALSE),"Various") -> Various | C54: Cargo and process piping - General | F54: IGC Code | G54: 5.2.1.4. Where tanks or piping are separated from the ship’s structure by thermal isolation, provision should be made for electrically bonding both the piping and the tanks. All gasketed pipe joints and hose connections should be electrically bonded.
A55: 635 690 | B55: =IFERROR(VLOOKUP(A55,Systems!A:B,2,FALSE),"Various") -> Various | C55: Cargo and process piping - General | F55: IGC Code | G55: 5.2.1.5. Suitable means should be provided to relieve the pressure and remove liquid contents from cargo loading and discharging crossover headers and cargo hoses to the cargo tanks or other suitable location, prior to disconnecting the cargo hoses.
A56: 635 690 | B56: =IFERROR(VLOOKUP(A56,Systems!A:B,2,FALSE),"Various") -> Various | C56: Cargo and process piping - General | F56: IGC Code | G56: 5.2.1.6. All pipelines or components which may be isolated in a liquid full condition should be provided with relief valves.
A57: 635 690 | B57: =IFERROR(VLOOKUP(A57,Systems!A:B,2,FALSE),"Various") -> Various | C57: Cargo and process piping - General | F57: IGC Code | G57: 5.2.1.7. Relief valves discharging liquid cargo from the cargo piping system should discharge into the cargo tanks; alternatively they may discharge to the cargo vent mast if means are provided to detect and dispose of any liquid cargo which may flow into the vent system. Relief valves on cargo pumps should discharge to the pump suction.
... A87: 635 | B87: =IFERROR(VLOOKUP(A87,Systems!A:B,2,FALSE),"Various") -> Cargo inerting systems | C87: Special Requirements - Flame screens on vent outlets | F87: IGC Code | G87: 17.10 Cargo tank vent outlets should be provided with readily renewable and effective flame screens or safety heads of an approved type when carrying a cargo referenced to this section. Due attention should be paid in the design of flame screens and vent heads to the possibility of the blockage of these devices by the freezing of cargo vapour or by icing up in adverse weather conditions. Ordinary protection screens should be fitted after removal of the flame screens.
A88: 102 31x 331 341 | B88: =IFERROR(VLOOKUP(A88,Systems!A:B,2,FALSE),"Various") -> Various | C88: Hull piping - Wall thickness | F88: Battery room | H88: B-6-7-5.2.1 The wall gross thickness of scuppers and discharge pipes is to be not less than the shell plating thickness in way of the scuppers, respectively discharge pipes, but need not exceed 8 mm. | P88: B-6-7-5.2.1 The wall gross thickness of scuppers and discharge pipes is to be not less than the shell plating thickness in way of the scuppers, respectively discharge pipes, but need not exceed 8 mm. | S88: x | U88: =IF(OR(NOT(H88=""),NOT(M88="")),"","x")
A89: 142 | B89: =IFERROR(VLOOKUP(A89,Systems!A:B,2,FALSE),"Various") -> Railings / handrails / grips | C89: Railing Arrangement | F89: Battery room | H89: B-7-2-2.1.1 - The outer edges of decks as well as work stations where persons might fall more than 1 m, shall be fitted with bulwarks or coamings that are at least 700 mm high or with a guard rail in accordance with European standard EN 711:1995, which shall comprise a handrail, a rail at knee height and a footrail. | P89: B-7-2-2.1.1 - The outer edges of decks as well as work stations where persons might fall more than 1 m, shall be fitted with bulwarks or coamings that are at least 700 mm high or with a guard rail in accordance with European standard EN 711:1995, which shall comprise a handrail, a rail at knee height and a footrail. | S89: x | U89: =IF(OR(NOT(H89=""),NOT(M89="")),"","x")
A90: 142 | B90: =IFERROR(VLOOKUP(A90,Systems!A:B,2,FALSE),"Various") -> Railings / handrails / grips | C90: Railing standard | F90: Battery room | H90: B-7-2-2.1.2 - The foot-guard is to rise at least 50 mm above the weather deck. B-7-2-2.2.1 - For passenger vessels, the bulwarks or guard rails are to be at least 1000 mm high above the decks open to passengers. In way of the aft deckhouse, a similar height is to be arranged. The foot-guard is to rise at least 50 mm above the weather deck. The opening below the lower course is not to be greater than 230 mm. The other courses are not to be more than 380 mm apart. Other standards may be accepted, in particular, bulwarks or guard rails in accordance with EN 711, Form PF, PG or PZ may be provided. | P90: B-7-2-2.1.2 - The foot-guard is to rise at least 50 mm above the weather deck. B-7-2-2.2.1 - For passenger vessels, the bulwarks or guard rails are to be at least 1000 mm high above the decks open to passengers. In way of the aft deckhouse, a similar height is to be arranged. The foot-guard is to rise at least 50 mm above the weather deck. The opening below the lower course is not to be greater than 230 mm. The other courses are not to be more than 380 mm apart. Other standards may be accepted, in particular, bulwarks or guard rails in accordance with EN 711, Form PF, PG or PZ may be provided. | S90: x | U90: =IF(OR(NOT(H90=""),NOT(M90="")),"","x")
A91: 371 | B91: =IFERROR(VLOOKUP(A91,Systems!A:B,2,FALSE),"Various") -> Ventilation system | C91: Closing appliances - General | F91: Battery room | H91: B-8-10-9.1.1 Ventilator openings are to be provided with efficient weathertight closing appliances of steel or other equivalent material. | S91: x | U91: =IF(OR(NOT(H91=""),NOT(M91="")),"","x")
A92: 371 | B92: =IFERROR(VLOOKUP(A92,Systems!A:B,2,FALSE),"Various") -> Ventilation system | C92: Closing appliance exemption | F92: Battery room | H92: B-8-10-9.1.2 Ventilators need not be fitted with closing appliances, unless specifically required by the Society, if the coamings extend for more than: 4,5 m above the deck in position 1 2,3 m above the deck in position 2. | S92: x | U92: =IF(OR(NOT(H92=""),NOT(M92="")),"","x")
A93: 371 | B93: =IFERROR(VLOOKUP(A93,Systems!A:B,2,FALSE),"Various") -> Ventilation system | C93: Ships of not more than 100 m in length | F93: Battery room | H93: B-8-10-9.1.3 In ships of not more than 100 m in length, the closing appliances are to be permanently attached to the ventilator coamings. | S93: x | U93: =IF(OR(NOT(H93=""),NOT(M93="")),"","x")
A94: 371 | B94: =IFERROR(VLOOKUP(A94,Systems!A:B,2,FALSE),"Various") -> Ventilation system | C94: Ships of more than 100 m in length | F94: Battery room | H94: B-8-10-9.1.4 Where, in ships of more than 100 m in length, the closing appliances are not permanently attached, they are to be conveniently stowed near the ventilators to which they are to be fitted. | S94: x | U94: =IF(OR(NOT(H94=""),NOT(M94="")),"","x")
A95: 371 | B95: =IFERROR(VLOOKUP(A95,Systems!A:B,2,FALSE),"Various") -> Ventilation system | C95: Ventilation of machinery spaces and emergency generator room | F95: Battery room | H95: B-8-10-9.1.5 In order to satisfactorily ensure, in all weather conditions: - the continuous ventilation of machinery spaces, - and, when necessary, the immediate ventilation of the emergency generator room, the ventilators serving such spaces are to comply with [9.1.2], i.e. their openings are to be so located that they do not require closing appliances. Note 1 : See also Pt C, Ch 4, Sec 2, [2.1] regarding closing appliances for ventilation systems. | S95: x | U95: =IF(OR(NOT(H95=""),NOT(M95="")),"","x")
A96: 371 | B96: =IFERROR(VLOOKUP(A96,Systems!A:B,2,FALSE),"Various") -> Ventilation system | C96: Reduced height of ventilator coamings for machinery spaces and emergency generator room | F96: Battery room | H96: B-8-10-9.1.6 Where, due to the ship's size and arrangement, the requirements in [9.1.5] are not practicable, lesser heights may be accepted for machinery space and emergency generator room ventilator coamings fitted with weathertight closing appliances in accordance with [9.1.1], [9.1.3] and [9.1.4] in combination with other suitable arrangements, such as separators fitted with drains, to ensure an uninterrupted, adequate supply of ventilation to these spaces. | S96: x | U96: =IF(OR(NOT(H96=""),NOT(M96="")),"","x")
A97: 371 | B97: =IFERROR(VLOOKUP(A97,Systems!A:B,2,FALSE),"Various") -> Ventilation system | C97: Closing arrangements of ventilators led overboard or through enclosed superstructures | F97: Battery room | H97: B-8-10-9.1.7 Closing arrangements of ventilators led overboard to the ship side or through enclosed superstructures are considered by the Society on a case by case basis. If such ventilators are led overboard more than 4,5 m above the freeboard deck, closing appliances may be omitted provided that satisfactory baffles and drainage arrangements are fitted. | S97: x | U97: =IF(OR(NOT(H97=""),NOT(M97="")),"","x")
A98: 371 | B98: =IFERROR(VLOOKUP(A98,Systems!A:B,2,FALSE),"Various") -> Ventilation system | C98: Table 7 | F98: Battery room | H98: B-8-10-9.1.7 Table 7 Height of the coaming, in mm, above the deck h = 900 in position 1 h = 760 in position 2 Thickness of the coaming, in mm (1) t = 5,5 + 0,01 dV with 7,5 ≤ t ≤ 10,0 Support If h > 900 mm, the coaming is to be suitably stiffened or supported by stays ( 1 ) Where the height of the ventilator exceeds the height h, the thickness of the coaming may be gradually reduced, above that height, to a minimum of 6,5 mm. dV : Internal diameter of the ventilator, in mm. | S98: x | T98: x | U98: =IF(OR(NOT(H98=""),NOT(M98="")),"","x")
A99: 371 | B99: =IFERROR(VLOOKUP(A99,Systems!A:B,2,FALSE),"Various") -> Ventilation system | C99: Coamings - General | F99: Battery room | H99: B-8-10-9.2.1 Ventilators in positions 1 or 2 to spaces below freeboard decks or decks of enclosed superstructures are to have coamings of steel or other equivalent material, substantially constructed and efficiently connected to the deck. Ventilators passing through superstructures other than enclosed superstructures are to have substantially constructed coamings of steel or other equivalent material at the freeboard deck. | S99: x | T99: x | U99: =IF(OR(NOT(H99=""),NOT(M99="")),"","x")
A100: 371 | B100: =IFERROR(VLOOKUP(A100,Systems!A:B,2,FALSE),"Various") -> Ventilation system | C100: Scantlings | F100: Battery room | H100: B-8-10-9.2.2 The scantlings of ventilator coamings exposed to the weather are to be not less than those obtained from Tab 7. In exposed locations or for the purpose of compliance with buoyancy calculations, the height of coamings may be required to be increased to the satisfaction of the Society. | U100: =IF(OR(NOT(H100=""),NOT(M100="")),"","x")
A101: 330 | B101: =IFERROR(VLOOKUP(A101,Systems!A:B,2,FALSE),"Various") -> Cooling water system | C101: Monitoring | F101: Battery room | H101: C-1-10 Table 28 Sea water pump pressure or flow Fresh water pump pressure or flow Low level alarm in cooling water expansion tank. | U101: =IF(OR(NOT(H101=""),NOT(M101="")),"","x")
A102: 311 312 32x 323 332 343 361 | B102: =IFERROR(VLOOKUP(A102,Systems!A:B,2,FALSE),"Various") -> Various | C102: Conditions of use of metallic materials in piping systems | F102: Battery room | H102: C-1-10 Table 5 Grey cast iron is not to be used for the following systems: - boiler blow-down systems and other piping systems subject to shocks, high stresses and vibrations - bilge lines in tanks - parts of scuppers and sanitary discharge systems located next to the hull below the freeboard deck or for passengers ships below the bulkhead deck - ship side valves and fittings - valves fitted on the collision bulkhead - valves fitted to fuel oil and lubricating oil tanks under static pressure head - class II fuel oil systems and thermal oil systems. | U102: =IF(OR(NOT(H102=""),NOT(M102="")),"","x")
A103: 222 | B103: =IFERROR(VLOOKUP(A103,Systems!A:B,2,FALSE),"Various") -> Steering gear system | C103: Pipe class | F103: Battery room | H103: C-1-10-1 table 3, remark 5 Steering gear hydraulic piping system belongs to class I irrespective of p and T. | U103: =IF(OR(NOT(H103=""),NOT(M103="")),"","x")
A104: 620 | B104: =IFERROR(VLOOKUP(A104,Systems!A:B,2,FALSE),"Various") -> Compressed air system | C104: Design pressure | F104: Battery room | H104: C-1-10-1.3.2.d The design pressure of a piping system located on the low pressure side of a pressure reducing valve where no safety valve is provided is not to be less than the maximum pressure on the high pressure side of the pressure reducing valve. | S104: N
A105: 300 | B105: =IFERROR(VLOOKUP(A105,Systems!A:B,2,FALSE),"Various") -> Piping common | C105: Protection against corrosion and erosion | F105: Battery room | H105: a. Pipes are to be efficiently protected against corrosion, particularly in their most exposed parts, either by selection of their constituent materials, or by an appropriate coating or treatment. b. The layout and arrangement of sea water pipes are to be such as to prevent sharp bends and abrupt changes in section as well as zones where water may stagnate. The inner surface of pipes is to be as smooth as possible, especially in way of joints. Where pipes are protected against corrosion by means of galvanising or other inner coating, arrangements are to be made so that this coating is continuous, as far as possible, in particular in way of joints. c. If galvanised steel pipes are used for sea water systems, the water velocity is not to exceed 3 m/s. d. If copper pipes are used for sea water systems, the water velocity is not to exceed 2 m/s. e. Arrangements are to be made to avoid galvanic corrosion. f. If aluminium bras pipes are used for sea water systems, the water velocity is not to exceed 3 m/s g. If 90/10 copper-nickel-iron pipes are used for sea water systems, the water velocity is not to exceed 3,5 m/s h. If 70/30 copper-nickel pipes are used for sea water systems, the water velocity is not to exceed 5 m/s i. If GRP pipes are used for sea water systems, the water velocity is not to exceed 5 m/s. | J105: a. Pipes are to be efficiently protected against corrosion, particularly in their most exposed parts, either by selection of their constituent materials, or by an appropriate coating or treatment b. The layout and arrangement of sea water pipes are to be such as to prevent sharp bends and abrupt changes in section as well as zones where water may stagnate. The inner surface of pipes is to be as smooth as possible, especially in way of joints. Where pipes are protected against corrosion by means of galvanising or other inner coating, arrangements are to be made so that this coating is continuous, as far as possible, in particular in way of joints c. If galvanised steel pipes are used for sea water systems, the water velocity is not to exceed 3 m/s d. If copper pipes are used for sea water systems, the water velocity is not to exceed 2 m/s e. Arrangements are to be made to avoid galvanic corrosion.
A106: 300 | B106: =IFERROR(VLOOKUP(A106,Systems!A:B,2,FALSE),"Various") -> Piping common | C106: Protection against frosting | F106: Battery room | H106: Pipes are to be adequately insulated against cold wherever deemed necessary to prevent frost. This applies specifically to pipes passing through refrigerated spaces and which are not intended to ensure the refrigeration of such spaces. | J106: Pipes are to be adequately insulated against cold wherever deemed necessary to prevent frost. This applies specifically to pipes passing through refrigerated spaces and which are not intended to ensure the refrigeration of such spaces.
A107: 300 | B107: =IFERROR(VLOOKUP(A107,Systems!A:B,2,FALSE),"Various") -> Piping common | C107: Protection against frosting | F107: Battery room | H107: a. All pipes and other components where the temperature may exceed 220°C are to be efficiently insulated. Where necessary, precautions are to be taken to protect the insulation from being impregnated with flammable oils. b. Particular attention is to be paid to lagging in way of flanges. | J107: a. All pipes and other components where the temperature may exceed 80°C are to be efficiently insulated. Where necessary, precautions are to be taken to protect the insulation from being impregnated with flammable oils. b. Particular attention is to be paid to lagging in way of flanges.
A108: 32x | B108: =IFERROR(VLOOKUP(A108,Systems!A:B,2,FALSE),"Various") -> Fuel-oil systems | C108: Additional requirements | F108: Battery room | H108: C-1-10-11.1.2 - for fuel oil supply equipment forming part of engines, gas turbines, boilers, thermal heaters and incinerators, in the corresponding sections - for the installation of purifiers, in Part C, Chapter 4, - for the location and scantling of tanks forming part of the ship's structure, in Part B, Chapter 2 and Part B, Chapter 7 - for helicopter refuelling facilities, in Ch 4, Sec 10, [4]. | S108: x | U108: =IF(OR(NOT(H108=""),NOT(M108="")),"","x")
A109: 32x 351 | B109: =IFERROR(VLOOKUP(A109,Systems!A:B,2,FALSE),"Various") -> Various | C109: Monitoring | F109: Battery room | H109: C-1-10-11.10.1 Alarms and safeguards are to be provided for fuel oil systems in accordance with Tab 29: Fuel oil overflow tank level - LAH - (or sightglas on the overflow pipe) Air pipe water trap level on fuel oil tanks - LAH - (or alternative arrangement as per [9.1.7], item c) Fuel oil temperature after heaters - LAH - local - (or low flow alarm in addition to temperature control when heated) (Automatic system shutdown) Sludge tank level - local Fuel oil settling tank temperature - LAH - local - (when heated) Fuel oil level in daily service tank - LAL + LAH - local - (or sightglas on the overflow pipe) Fuel oil daily service tank temperature - LAH - local - (when heated) | S109: x | T109: x | U109: =IF(OR(NOT(H109=""),NOT(M109="")),"","x")
A110: 322 430 | B110: =IFERROR(VLOOKUP(A110,Systems!A:B,2,FALSE),"Various") -> Various | C110: Automatic controls | F110: Battery room | H110: C-1-10-11.10.2 Automatic temperature control is to be provided for: - steam heaters or heaters using other media - electric heaters. | S110: x | U110: =IF(OR(NOT(H110=""),NOT(M110="")),"","x")
A111: 321 | B111: =IFERROR(VLOOKUP(A111,Systems!A:B,2,FALSE),"Various") -> Fuel transfer system | C111: Remote controls | F111: Battery room | H111: C-1-10-11.10.3.a The remote control arrangement of valves fitted on fuel oil tanks is to comply with [11.6.4]. | S111: x
A112: 322 | B112: =IFERROR(VLOOKUP(A112,Systems!A:B,2,FALSE),"Various") -> Fuel supply system | C112: Power supply to fuel equipment | F112: Battery room | H112: C-1-10-11.10.3.b The power supply to: - fuel oil burning pumps - transfer pumps and other pumps of the fuel oil system, and - fuel oil purifiers, is to be capable of being stopped from a position within the space containing the pumps and from another position located outside such space and always accessible in the event of fire within the space.
A113: 322 | B113: =IFERROR(VLOOKUP(A113,Systems!A:B,2,FALSE),"Various") -> Fuel supply system | C113: Valve control emergency generator fuel tank | F113: Battery room | H113: C-1-10-11.10.3.c Remote control of the valve fitted to the emergency generator fuel tank is to be in a separate location from that of other valves fitted to tanks in the engine room. "Separate location" does not mean separate spaces. | S113: x
A114: 321 | B114: =IFERROR(VLOOKUP(A114,Systems!A:B,2,FALSE),"Various") -> Fuel transfer system | C114: Remote control of the valve fitted onto emergency generator fuel tank | F114: Battery room | H114: C-1-10-11.10.3.c Remote control of the valve fitted to the emergency generator fuel tank is to be in a separate location from that of other valves fitted to tanks in the engine room. "Separate location" does not mean separate spaces. | S114: x | T114: x | U114: =IF(OR(NOT(H114=""),NOT(M114="")),"","x")
A115: 32x | B115: =IFERROR(VLOOKUP(A115,Systems!A:B,2,FALSE),"Various") -> Fuel-oil systems | C115: Positions of the remote controls | F115: Battery room | H115: C-1-10-11.10.3.d The positions of the remote controls are also to comply with Part C, Chapter 3.
A116: 32x | B116: =IFERROR(VLOOKUP(A116,Systems!A:B,2,FALSE),"Various") -> Fuel-oil systems | C116: Materials | F116: Battery room | H116: C-1-10-11.11.1 a. Fuel oil pipes and their valves are to be of steel or other approved material, except that the use of flexible pipes may be accepted provided they comply with [2.6.3]. b. The materials and/or their surface treatment used for the storage and distribution of oil fuel are to be selected such that they do not introduce contamination or modify the properties of the fuel. In addition to the criterion given in Tab 5, the use of copper or zinc compounds in oil fuel distribution and utilisation piping is not permitted except for small diameter pipes in low pressure systems. | J116: 2-6-1.3.1 Materials and details Materials used for piping and equipment as well as general details are to be in compliance with Sec 4. Materials and/or the surface treatment used for the storage and distribution of fuel oil are to be selected such that they do not introduce contamination or modify the properties of fuel.
A117: 32x | B117: =IFERROR(VLOOKUP(A117,Systems!A:B,2,FALSE),"Various") -> Fuel-oil systems | C117: Pipe thickness | F117: Battery room | H117: C-1-10-11.11.2 The thickness of pipes conveying heated fuel oil, as well as their flanges, is to be calculated for a design pressure determined in accordance with Tab 4.
A118: 32x | B118: =IFERROR(VLOOKUP(A118,Systems!A:B,2,FALSE),"Various") -> Fuel-oil systems | C118: Pipe connections | F118: Battery room | H118: C-1-10-11.11.3 - Connections and fittings of pipes containing fuel oil are to be suitable for a design pressure according to Tab 3 and Tab 4. - Connections of pipes conveying heated fuel oil are to be made by means of close-fitting flanges, with joints made of a material impervious to oil heated to 160°C and as thin as possible.
A119: 32x | B119: =IFERROR(VLOOKUP(A119,Systems!A:B,2,FALSE),"Various") -> Fuel-oil systems | C119: Passage of fuel oil pipes through tanks | F119: Battery room | H119: C-1-10-11.12.1 a. Fuel pipes are not to pass through tanks containing boiler feed water, fresh water, other flammable oil or liquid cargo, unless they are contained within tunnels. b. Transfer pipes passing through ballast tanks are to have a reinforced thickness complying with Tab 6.
A120: 32x | B120: =IFERROR(VLOOKUP(A120,Systems!A:B,2,FALSE),"Various") -> Fuel-oil systems | C120: Passage of pipes through fuel oil tanks | F120: Battery room | H120: C-1-10-11.12.2 Boiler feed water, fresh water or liquid cargo pipes are not to pass through fuel oil tanks, unless such pipes are contained within tunnels. | S120: x | T120: x | U120: =IF(OR(NOT(H120=""),NOT(M120="")),"","x")
A121: 322 | B121: =IFERROR(VLOOKUP(A121,Systems!A:B,2,FALSE),"Various") -> Fuel supply system | C121: Segregation of fuel oil purifiers | F121: Battery room | H121: C-1-10-11.12.3 Purifiers for heated fuel oil are to be in accordance with Ch 4, Sec 6, [4.1.2]. | S121: x | T121: x | U121: =IF(OR(NOT(H121=""),NOT(M121="")),"","x")
A122: 321 | B122: =IFERROR(VLOOKUP(A122,Systems!A:B,2,FALSE),"Various") -> Fuel transfer system | C122: General | F122: Battery room | H122: C-1-10-11.2.1 a. Fuel oil systems are to be so designed as to ensure the proper characteristics (purity, viscosity, pressure) of the fuel oil supply to engines and boilers. b. Fuel oil systems are to be so designed as to prevent: - overflow or spillage of fuel oil from tanks, pipes, fittings, etc. - fuel oil from coming into contact with sources of ignition - overheating and seizure of fuel oil. c. Fuel oils used for engines and boilers are to have a flashpoint complying with the provisions of Ch 1, Sec 1, [2.9]. | S122: x | T122: x | U122: =IF(OR(NOT(H122=""),NOT(M122="")),"","x")
A123: 32x | B123: =IFERROR(VLOOKUP(A123,Systems!A:B,2,FALSE),"Various") -> Fuel-oil systems | C123: Availability | F123: Battery room | H123: C-1-10-11.2.2 a. Fuel oil systems are to be so designed that, in the event that any one essential auxiliary of such systems becomes inoperative, the fuel oil supply to boilers and engines can be maintained. Partial reduction of the propulsion capability may be accepted, however, when it is demonstrated that the safe operation of the ship is not impaired. b. Fuel oil tanks are to be so arranged that, in the event of damage to any one tank, complete loss of the fuel supply to essential services does not occur. c. Where engines and boilers are operated with heavy fuel oils, provisions are to be made to supply them with fuel oils which do not need to be heated. | S123: x | T123: x | U123: =IF(OR(NOT(H123=""),NOT(M123="")),"","x")
A124: 32x | B124: =IFERROR(VLOOKUP(A124,Systems!A:B,2,FALSE),"Various") -> Fuel-oil systems | C124: Arrangement | F124: Battery room | H124: C-1-10-11.3.1 a. In a ship in which fuel oil is used, the arrangements for the storage, distribution and utilisation of the fuel oil are to be such as to ensure the safety of the ship and persons on board. b. The provisions of [5.10] are to be complied with. | S124: x | T124: x | U124: =IF(OR(NOT(H124=""),NOT(M124="")),"","x")
A125: 32x | B125: =IFERROR(VLOOKUP(A125,Systems!A:B,2,FALSE),"Various") -> Fuel-oil systems | C125: Overpressure | F125: Battery room | H125: C-1-10-11.3.2 Provisions are to be made to prevent overpressure in any oil tank or in any part of the fuel oil system. Any relief valve is to discharge to a safe position. | S125: x | T125: x | U125: =IF(OR(NOT(H125=""),NOT(M125="")),"","x")
A126: 321 | B126: =IFERROR(VLOOKUP(A126,Systems!A:B,2,FALSE),"Various") -> Fuel transfer system | C126: Design of fuel oil filling and transfer systems | F126: Battery room | H126: C-1-10-11.4.1 General a) A system of pumps and piping for filling and transferring fuel oil is to be provided. b) Provisions are to be made to allow the transfer of fuel oil from any storage, settling or service tank to another tank. | S126: x | T126: x | U126: =IF(OR(NOT(H126=""),NOT(M126="")),"","x")
A127: 321 | B127: =IFERROR(VLOOKUP(A127,Systems!A:B,2,FALSE),"Various") -> Fuel transfer system | C127: General design | F127: Battery room | H127: C-1-10-11.4.1 a. A system of pumps and piping for filling and transferring fuel oil is to be provided. b. Provisions are to be made to allow the transfer of fuel oil from any storage, settling or service tank to another tank. | S127: x | T127: x | U127: =IF(OR(NOT(H127=""),NOT(M127="")),"","x")
A128: 321 | B128: =IFERROR(VLOOKUP(A128,Systems!A:B,2,FALSE),"Various") -> Fuel transfer system | C128: Design of fuel oil filling and transfer systems | F128: Battery room | H128: C-1-10-11.4.2 Filling systems a) Filling pipes of fuel oil tanks are to terminate on open deck or in filling stations isolated from other spaces and efficiently ventilated. Suitable coamings and drains are to be provided to collect any leakage resulting from filling operations. The means shall be provided for the filling lines to prevent of possible overpressure during the bunkering operation, which could be caused by pumps from outboard filling station. For that purpose a warning label may be accepted with clearly declared design pressure of the filling lines and the local pressure gauge fitted in vicinity of the filling connection. b) Arrangements are to be made to avoid overpressure in the filling lines which are served by pumps on board. Where safety valves are provided for this purpose, they are to discharge to the overflow tank referred to in [9.3.3] or to other safe positions deemed satisfactory. | S128: x | T128: x | U128: =IF(OR(NOT(H128=""),NOT(M128="")),"","x")
A129: 321 | B129: =IFERROR(VLOOKUP(A129,Systems!A:B,2,FALSE),"Various") -> Fuel transfer system | C129: Filling system | F129: Battery room | H129: C-1-10-11.4.2 a. Filling pipes of fuel oil tanks are to terminate on open deck or in filling stations isolated from other spaces and efficiently ventilated. Suitable coamings and drains are to be provided to collect any leakage resulting from filling operations. The means shall be provided for the filling lines to prevent of possible overpressure during the bunkering operation, which could be caused by pumps from outboard filling station. For that purpose a warning label may be accepted with clearly declared design pressure of the filling lines and the local pressure gauge fitted in vicinity of the filling connection. b. Arrangements are to be made to avoid overpressure in the filling lines which are served by pumps on board. Where safety valves are provided for this purpose, they are to discharge to the overflow tank referred to in [9.3.3] or to other safe positions deemed satisfactory. | S129: x | T129: x | U129: =IF(OR(NOT(H129=""),NOT(M129="")),"","x")
...

Sheet Tables
A70: Wallthicknesses
A72: Steel pipes | I72: CO2 systems | R72: Copper and copper alloy pipes | W72: Stainless steel pipes | AJ72: Aluminium and aluminium alloy pipes

Sheet Public root
B3: Division | C3: Mechanical
B5: Bureau Veritas eRules | C5: Rules for the Classification of Inland Navigation Vessels - November 2014 edition (entry into force 1 February 2015)
B7: Ministry of Transportation of Ontario | C7: Technical Specification for the Design, Construction and Delivery of a 40 Vehicle Roll-on / Roll-off Passenger (Ro-Pax) Ferry

Sheet Systems
A1: SYSTEM | B1: DESCRIPTION
A2: 000 | B2: Project data
A3: 100 | B3: Tank arrangement
A4: 102 | B4: Hull connections
A5: 130 | B5: Hatches / doors / windows
A6: 131 | B6: Hatches
A7: 132 | B7: Manholes / manhole covers
A8: 133
A9: 134
A10: 135
A11: 136
A12: 137
A13: 139
A14: 140
A15: 141 | B15: Stairs / ladders / climbing steps
A16: 142 | B16: Railings / handrails / grips
A17: 143 | B17: Platforms / gratings
A18: 144
A19: 163 | B19: Cathodic protection
A20: 200 | B20: Main machinery
A21: 201
A22: 202
A23: 203
A24: 204
A25: 210
A26: 211 | B26: Propulsion engine system
A27: 212 | B27: Reduction gear system
A28: 213 | B28: Thrust systems / shafts
A29: 214
A30: 220
A31: 221
A32: 222 | B32: Steering gear system
A33: 223
A34: 224
A35: 250
A36: 251
A37: 252
A38: 253
A39: 254
A40: 255
A41: 256
A42: 257
A43: 258
A44: 259
A45: 295
A46: 300 | B46: Piping common
A47: 303 | B47: Inspection of welded joints
A48: 3xx | B48: Mechanical systems
A49: 310 | B49: Bilge / ballast / internal fifi
A50: 311 | B50: Bilge system
A51: 312 | B51: Ballast system
A52: 313 | B52: Deckwash / internal fifi system
A53: 31x | B53: Bilge / ballast / internal fifi
A54: 320 | B54: Fuel system
A55: 321 | B55: Fuel transfer system
A56: 322 | B56: Fuel supply system
A57: 323 | B57: Domestic tank heating system
... A85: 380 | B85: Exhaust system
A86: 381
A87: 382 | B87: Exhaust gas cleaning system
A88: 390
A89: 391
A90: 393 | B90: Remote controlled valves
A91: 400
A92: 401 | B92: Cable trays and penetrations
A93: 402
A94: 403
A95: 404
A96: 410 | B96: Power generating system
A97: 411 | B97: Generator sets
A98: 412 | B98: Shaft generators
A99: 413 | B99: Electrical motors
A100: 414 | B100: Frequency drives
A101: 410 | B101: Power generating system
A102: 420 | B102: Cables
A103: 430 | B103: Switchboards & components
A104: 440 | B104: Alarm / monitoring / control system
A105: 450 | B105: Lighting
A106: 610 | B106: Hydraulic system
A107: 620 | B107: Compressed air system
... A124: 741 | B124: Engine room arrangement

Sheet Data
B2: Yes/no
B3: Yes
B4: No
B6: Publications
B7: NR467 Steelships - July 2018 edition (entry into force 1 July 2018)
B8: NR216 Materials and welding - Januari
B9: Offshore units
B10: Yachts
B11: Inland
B12: Floating
B13: Naval
B14: NR600
... B50: VCS
